vto/__init__.py
vto/_samples.py
vto-0.0.0.1.dist-info/LICENSE
vto-0.0.0.1.dist-info/METADATA
vto-0.0.0.1.dist-info/WHEEL
vto-0.0.0.1.dist-info/top_level.txt
vto-0.0.0.1.dist-info/RECORD
